setup.py
sage_modabvar/__init__.py
sage_modabvar/abvar.py
sage_modabvar/abvar_ambient_jacobian.py
sage_modabvar/abvar_newform.py
sage_modabvar/constructor.py
sage_modabvar/cuspidal_subgroup.py
sage_modabvar/finite_subgroup.py
sage_modabvar/homology.py
sage_modabvar/homspace.py
sage_modabvar/lseries.py
sage_modabvar/morphism.py
sage_modabvar/torsion_point.py
sage_modabvar/torsion_subgroup.py
sage_modabvar.egg-info/PKG-INFO
sage_modabvar.egg-info/SOURCES.txt
sage_modabvar.egg-info/dependency_links.txt
sage_modabvar.egg-info/not-zip-safe
sage_modabvar.egg-info/top_level.txt