Metadata-Version: 1.0
Name: sage-modabvar
Version: 0.1
Summary: Modular Abelian Varieties
Home-page: ...todo...
Author: William Stein, ...
Author-email: wstein@gmail.com
License: GPLv3
Platform: UNKNOWN
